dingTalk_notify/__init__.py
dingTalk_notify/plugin.py
dingTalk_notify_source/__init__.py
dingTalk_notify_source/plugin.py
dingTalk_notify_to_people/__init__.py
dingTalk_notify_to_people/plugin.py
dingTalk_notify_source-1.0.1.dist-info/LICENSE
dingTalk_notify_source-1.0.1.dist-info/METADATA
dingTalk_notify_source-1.0.1.dist-info/WHEEL
dingTalk_notify_source-1.0.1.dist-info/entry_points.txt
dingTalk_notify_source-1.0.1.dist-info/top_level.txt
dingTalk_notify_source-1.0.1.dist-info/RECORD
